trelent/auth_module.py
trelent/docgen.py
trelent/main.py
trelent/utils.py
trelent-1.0.dist-info/LICENSE
trelent-1.0.dist-info/METADATA
trelent-1.0.dist-info/WHEEL
trelent-1.0.dist-info/entry_points.txt
trelent-1.0.dist-info/top_level.txt
trelent-1.0.dist-info/RECORD
