Metadata-Version: 2.1
Name: trelent
Version: 1.0
Summary: A command line tool to generate documentation
Home-page: https://trelent.net
Author: Trelent Inc.
Author-email: contact@trelent.net
License: UNKNOWN
Platform: UNKNOWN
Classifier: Operating System :: OS Independent
License-File: LICENSE
Requires-Dist: Click
Requires-Dist: Requests
